django_admin_display/__init__.py
django_admin_display/py.typed
django_admin_display-1.3.0.dist-info/LICENSE
django_admin_display-1.3.0.dist-info/WHEEL
django_admin_display-1.3.0.dist-info/METADATA
django_admin_display-1.3.0.dist-info/RECORD
